README.md
setup.py
huetainment_api/__init__.py
huetainment_api/api_client.py
huetainment_api/configuration.py
huetainment_api/rest.py
huetainment_api.egg-info/PKG-INFO
huetainment_api.egg-info/SOURCES.txt
huetainment_api.egg-info/dependency_links.txt
huetainment_api.egg-info/requires.txt
huetainment_api.egg-info/top_level.txt
huetainment_api/api/__init__.py
huetainment_api/api/settings_api.py
huetainment_api/api/states_api.py
huetainment_api/models/__init__.py
huetainment_api/models/setting_capture_device.py
huetainment_api/models/setting_capture_interval.py
huetainment_api/models/setting_capture_margins.py
huetainment_api/models/setting_capture_multiplier.py
huetainment_api/models/setting_capture_video_standard.py
huetainment_api/models/setting_center_slowness.py
huetainment_api/models/setting_chroma_boost.py
huetainment_api/models/setting_color_bias.py
huetainment_api/models/setting_luma_boost.py
huetainment_api/models/setting_max_luminance.py
huetainment_api/models/setting_min_luminance.py
huetainment_api/models/setting_side_slowness.py
huetainment_api/models/setting_syncing_group.py
huetainment_api/models/settings.py
huetainment_api/models/state_capturing.py
huetainment_api/models/state_syncing.py
huetainment_api/models/states.py
test/__init__.py
test/test_setting_capture_device.py
test/test_setting_capture_interval.py
test/test_setting_capture_margins.py
test/test_setting_capture_multiplier.py
test/test_setting_capture_video_standard.py
test/test_setting_center_slowness.py
test/test_setting_chroma_boost.py
test/test_setting_color_bias.py
test/test_setting_luma_boost.py
test/test_setting_max_luminance.py
test/test_setting_min_luminance.py
test/test_setting_side_slowness.py
test/test_setting_syncing_group.py
test/test_settings.py
test/test_settings_api.py
test/test_state_capturing.py
test/test_state_syncing.py
test/test_states.py
test/test_states_api.py