Metadata-Version: 1.0
Name: huetainment-api
Version: 1.0.0
Summary: huetainment API
Home-page: UNKNOWN
Author: UNKNOWN
Author-email: cbro@semperpax.com
License: UNKNOWN
Keywords: Swagger,huetainment API
Platform: UNKNOWN
